{"file":"laohujinew004.png","frames":{"img_laohujinew001_chuzuanshi":{"h":98,"offX":0,"offY":12,"w":120,"x":173,"y":373},"img_laohujinew001_kuang001":{"h":116,"offX":1,"offY":1,"w":116,"x":0,"y":373},"img_laohujinew001yc_penjiu001":{"h":58,"offX":4,"offY":9,"w":151,"x":455,"y":666},"img_laohujinew001yc_penjiu002":{"h":60,"offX":7,"offY":8,"w":150,"x":0,"y":608},"img_laohujinew001yc_penjiu003":{"h":52,"offX":9,"offY":7,"w":144,"x":582,"y":907},"img_laohujinew001yc_penjiu004":{"h":53,"offX":7,"offY":10,"w":143,"x":293,"y":918},"img_laohujinew001yc_penjiu005":{"h":53,"offX":5,"offY":9,"w":152,"x":749,"y":766},"img_laohujinew001yc_penjiu006":{"h":56,"offX":9,"offY":9,"w":146,"x":145,"y":846},"img_laohujinew001yc_penjiu007":{"h":50,"offX":7,"offY":9,"w":146,"x":145,"y":904},"img_laohujinew001yc_penjiu008":{"h":61,"offX":5,"offY":9,"w":149,"x":304,"y":609},"img_laohujinew001yc_penjiu009":{"h":61,"offX":9,"offY":9,"w":144,"x":0,"y":733},"img_laohujinew001yc_penjiu010":{"h":60,"offX":7,"offY":9,"w":143,"x":0,"y":796},"img_laohujinew001yc_penjiu011":{"h":58,"offX":5,"offY":9,"w":151,"x":608,"y":666},"img_laohujinew001yc_penjiu012":{"h":58,"offX":10,"offY":9,"w":144,"x":298,"y":798},"img_laohujinew001yc_penjiu013":{"h":55,"offX":7,"offY":9,"w":151,"x":761,"y":709},"img_laohujinew001yc_penjiu014":{"h":56,"offX":5,"offY":9,"w":150,"x":452,"y":726},"img_laohujinew001yc_penjiu015":{"h":58,"offX":9,"offY":9,"w":145,"x":444,"y":839},"img_laohujinew001yc_penjiu016":{"h":57,"offX":7,"offY":9,"w":145,"x":591,"y":848},"img_laohujinew001yc_penjiu017":{"h":53,"offX":5,"offY":8,"w":152,"x":444,"y":784},"img_laohujinew001yc_penjiu018":{"h":59,"offX":9,"offY":8,"w":149,"x":301,"y":672},"img_laohujinew001yc_penjiu019":{"h":50,"offX":9,"offY":7,"w":144,"x":728,"y":935},"img_laohujinew001yc_penjiu020":{"h":57,"offX":7,"offY":7,"w":148,"x":150,"y":731},"img_laohujinew001yc_penjiu021":{"h":61,"offX":4,"offY":6,"w":150,"x":798,"y":586},"img_laohujinew001yc_penjiu022":{"h":55,"offX":10,"offY":6,"w":142,"x":438,"y":899},"img_laohujinew001yc_penjiu023":{"h":65,"offX":7,"offY":5,"w":147,"x":339,"y":542},"img_laohujinew001yc_penjiu024":{"h":65,"offX":5,"offY":5,"w":148,"x":82,"y":541},"img_laohujinew001yc_penjiu025":{"h":63,"offX":9,"offY":5,"w":142,"x":300,"y":733},"img_laohujinew001yc_penjiu026":{"h":66,"offX":7,"offY":4,"w":149,"x":118,"y":473},"img_laohujinew001yc_penjiu027":{"h":63,"offX":4,"offY":4,"w":151,"x":520,"y":540},"img_laohujinew001yc_penjiu028":{"h":63,"offX":9,"offY":4,"w":143,"x":604,"y":726},"img_laohujinew001yc_penjiu029":{"h":60,"offX":7,"offY":4,"w":150,"x":152,"y":608},"img_laohujinew001yc_penjiu030":{"h":59,"offX":4,"offY":4,"w":151,"x":641,"y":605},"img_laohujinew001yc_penjiu031":{"h":61,"offX":9,"offY":4,"w":148,"x":0,"y":670},"img_laohujinew001yc_penjiu032":{"h":54,"offX":5,"offY":7,"w":150,"x":749,"y":821},"img_laohujinew001yc_penjiu033":{"h":55,"offX":7,"offY":6,"w":149,"x":598,"y":791},"img_laohujinew001yc_penjiu034":{"h":58,"offX":10,"offY":5,"w":143,"x":293,"y":858},"img_laohujinew001yc_penjiu035":{"h":59,"offX":4,"offY":5,"w":151,"x":488,"y":605},"img_laohujinew001yc_penjiu036":{"h":54,"offX":7,"offY":5,"w":150,"x":146,"y":790},"img_laohujinew001yc_penjiu037":{"h":59,"offX":9,"offY":4,"w":143,"x":0,"y":858},"img_laohujinew001yc_penjiu038":{"h":58,"offX":4,"offY":4,"w":151,"x":794,"y":649},"img_laohujinew001yc_penjiu039":{"h":59,"offX":7,"offY":4,"w":149,"x":150,"y":670},"img_laohujinew001yc_penxiangbin066":{"h":56,"offX":9,"offY":9,"w":144,"x":738,"y":877},"img_laohujitexiao002_zisebao001":{"h":187,"offX":13,"offY":4,"w":179,"x":558,"y":0},"img_laohujitexiao002_zisebao002":{"h":189,"offX":8,"offY":7,"w":182,"x":374,"y":0},"img_laohujitexiao002_zisebao003":{"h":192,"offX":7,"offY":7,"w":185,"x":187,"y":0},"img_laohujitexiao002_zisebao004":{"h":192,"offX":7,"offY":7,"w":185,"x":0,"y":0},"img_laohujitexiao002_zisebao005":{"h":186,"offX":13,"offY":7,"w":178,"x":739,"y":188},"img_laohujitexiao002_zisebao006":{"h":186,"offX":13,"offY":7,"w":178,"x":739,"y":0},"img_laohujitexiao002_zisebao007":{"h":168,"offX":11,"offY":16,"w":166,"x":352,"y":372},"img_laohujitexiao002_zisebao008":{"h":168,"offX":11,"offY":16,"w":166,"x":552,"y":370},"img_laohujitexiao002_zisebao009":{"h":179,"offX":4,"offY":13,"w":176,"x":558,"y":189},"img_laohujitexiao002_zisebao010":{"h":179,"offX":4,"offY":13,"w":176,"x":374,"y":191},"img_laohujitexiao002_zisebao011":{"h":177,"offX":5,"offY":14,"w":174,"x":176,"y":194},"img_laohujitexiao002_zisebao012":{"h":177,"offX":5,"offY":14,"w":174,"x":0,"y":194},"img_laohujitexiao004_baoshguang01":{"h":25,"offX":65,"offY":50,"w":35,"x":295,"y":412},"img_laohujitexiao004_baoshguang02":{"h":64,"offX":44,"offY":30,"w":68,"x":269,"y":538},"img_laohujitexiao004_baoshguang03":{"h":60,"offX":28,"offY":33,"w":88,"x":919,"y":65},"img_laohujitexiao004_baoshguang04":{"h":64,"offX":37,"offY":27,"w":77,"x":917,"y":397},"img_laohujitexiao004_baoshguang05":{"h":65,"offX":37,"offY":30,"w":77,"x":919,"y":330},"img_laohujitexiao004_baoshguang06":{"h":63,"offX":37,"offY":34,"w":77,"x":913,"y":463},"img_laohujitexiao004_baoshguang07":{"h":57,"offX":37,"offY":36,"w":76,"x":720,"y":532},"img_laohujitexiao004_baoshguang08":{"h":70,"offX":41,"offY":32,"w":78,"x":919,"y":127},"img_laohujitexiao004_baoshguang09":{"h":63,"offX":27,"offY":35,"w":90,"x":919,"y":0},"img_laohujitexiao004_baoshguang10":{"h":63,"offX":31,"offY":30,"w":84,"x":919,"y":199},"img_laohujitexiao004_baoshguang11":{"h":64,"offX":33,"offY":33,"w":82,"x":919,"y":264},"img_laohujitexiao004_baoshguang12":{"h":63,"offX":38,"offY":31,"w":76,"x":269,"y":473},"img_laohujitexiao004_baoshguang13":{"h":56,"offX":35,"offY":36,"w":77,"x":886,"y":528},"img_laohujitexiao004_baoshguang14":{"h":54,"offX":28,"offY":37,"w":83,"x":720,"y":476},"img_laohujitexiao004_baoshguang15":{"h":54,"offX":32,"offY":32,"w":79,"x":805,"y":511},"img_laohujitexiao004_baoshguang16":{"h":56,"offX":28,"offY":34,"w":80,"x":0,"y":491},"img_laohujitexiao004_baoshguang17":{"h":68,"offX":34,"offY":30,"w":73,"x":842,"y":376},"img_laohujitexiao004_baoshguang18":{"h":63,"offX":38,"offY":32,"w":69,"x":842,"y":446},"img_laohujitexiao004_baoshguang19":{"h":56,"offX":40,"offY":36,"w":59,"x":0,"y":549},"img_laohujitexiao004_baoshguang20":{"h":54,"offX":45,"offY":37,"w":53,"x":118,"y":373},"img_laohujitexiao004_baoshguang21":{"h":37,"offX":55,"offY":38,"w":41,"x":295,"y":373},"img_laohujitexiao004_baoshguang22":{"h":37,"offX":85,"offY":38,"w":11,"x":1011,"y":0},"img_laohujitexiao004_chuzuanshi":{"h":98,"offX":0,"offY":12,"w":120,"x":720,"y":376}}}
